keycardai/mcp/client/CONTRIBUTORS.md
keycardai/mcp/client/README.md
keycardai/mcp/client/__init__.py
keycardai/mcp/client/client.py
keycardai/mcp/client/context.py
keycardai/mcp/client/exceptions.py
keycardai/mcp/client/logging_config.py
keycardai/mcp/client/manager.py
keycardai/mcp/client/session.py
keycardai/mcp/client/session.pyi
keycardai/mcp/client/types.py
keycardai/mcp/client/auth/__init__.py
keycardai/mcp/client/auth/events.py
keycardai/mcp/client/auth/handlers.py
keycardai/mcp/client/auth/protocols.py
keycardai/mcp/client/auth/storage_facades.py
keycardai/mcp/client/auth/transports.py
keycardai/mcp/client/auth/coordinators/__init__.py
keycardai/mcp/client/auth/coordinators/base.py
keycardai/mcp/client/auth/coordinators/endpoint_managers.py
keycardai/mcp/client/auth/coordinators/local.py
keycardai/mcp/client/auth/coordinators/remote.py
keycardai/mcp/client/auth/oauth/__init__.py
keycardai/mcp/client/auth/oauth/_client.py
keycardai/mcp/client/auth/oauth/discovery.py
keycardai/mcp/client/auth/oauth/exchange.py
keycardai/mcp/client/auth/oauth/flow.py
keycardai/mcp/client/auth/oauth/registration.py
keycardai/mcp/client/auth/strategies/__init__.py
keycardai/mcp/client/auth/strategies/oauth.py
keycardai/mcp/client/connection/__init__.py
keycardai/mcp/client/connection/base.py
keycardai/mcp/client/connection/factory.py
keycardai/mcp/client/connection/http.py
keycardai/mcp/client/integrations/__init__.py
keycardai/mcp/client/integrations/auth_tools.py
keycardai/mcp/client/integrations/crewai_agents.py
keycardai/mcp/client/integrations/langchain_agents.py
keycardai/mcp/client/integrations/openai_agents.py
keycardai/mcp/client/integrations/pydantic_agents.py
keycardai/mcp/client/storage/__init__.py
keycardai/mcp/client/storage/backend.py
keycardai/mcp/client/storage/namespaced.py
keycardai/mcp/client/storage/path_builder.py
keycardai/mcp/client/storage/backends/__init__.py
keycardai/mcp/client/storage/backends/memory.py
keycardai/mcp/client/storage/backends/sqlite.py
keycardai_mcp-0.20.0.dist-info/METADATA
keycardai_mcp-0.20.0.dist-info/WHEEL
keycardai_mcp-0.20.0.dist-info/RECORD
