Metadata-Version: 2.4
Name: keycardai-mcp
Version: 0.20.0
Summary: A Python SDK for Model Context Protocol (MCP) functionality with simplified authentication and authorization
Project-URL: Homepage, https://github.com/keycardai/python-sdk
Project-URL: Repository, https://github.com/keycardai/python-sdk
Project-URL: Documentation, https://docs.keycardai.com
Project-URL: Issues, https://github.com/keycardai/python-sdk/issues
Author-email: Keycard <support@keycard.ai>
License: MIT
Keywords: ai,authentication,authorization,llm,mcp,model-context-protocol
Classifier: Development Status :: 3 - Alpha
Classifier: Intended Audience :: Developers
Classifier: License :: OSI Approved :: MIT License
Classifier: Operating System :: OS Independent
Classifier: Programming Language :: Python :: 3
Classifier: Programming Language :: Python :: 3.10
Classifier: Programming Language :: Python :: 3.11
Classifier: Programming Language :: Python :: 3.12
Classifier: Programming Language :: Python :: 3.13
Classifier: Topic :: Internet :: WWW/HTTP :: Session
Classifier: Topic :: Scientific/Engineering :: Artificial Intelligence
Classifier: Topic :: Security
Classifier: Topic :: Software Development :: Libraries :: Python Modules
Requires-Python: >=3.10
Requires-Dist: aiohttp>=3.11.11
Requires-Dist: aiosqlite>=0.20.0
Requires-Dist: httpx>=0.27.2
Requires-Dist: keycardai-oauth>=0.6.0
Requires-Dist: mcp>=1.13.1
Requires-Dist: nanoid>=2.0.0
Requires-Dist: pydantic>=2.11.7
Requires-Dist: starlette>=0.47.3
Provides-Extra: crewai
Requires-Dist: crewai>=0.86.0; extra == 'crewai'
Requires-Dist: nest-asyncio>=1.6.0; extra == 'crewai'
Provides-Extra: pydantic-ai
Requires-Dist: pydantic-ai>=0.2.0; extra == 'pydantic-ai'
Provides-Extra: test
Requires-Dist: crewai>=0.86.0; extra == 'test'
Requires-Dist: fastmcp>=2.13.0; extra == 'test'
Requires-Dist: keycardai-mcp-fastmcp; extra == 'test'
Requires-Dist: langchain-openai>=1.0.2; extra == 'test'
Requires-Dist: langchain>=1.0.5; extra == 'test'
Requires-Dist: openai-agents>=0.5.1; extra == 'test'
Requires-Dist: pydantic-ai>=0.2.0; extra == 'test'
Requires-Dist: pytest-asyncio>=1.1.0; extra == 'test'
Requires-Dist: pytest-cov>=6.2.1; extra == 'test'
Requires-Dist: pytest-timeout>=2.3.1; extra == 'test'
Requires-Dist: pytest>=8.4.1; extra == 'test'
